CHANGES.txt
LICENSE.txt
MANIFEST.in
README.txt
setup.py
loggerglue/__init__.py
loggerglue/rfc5424.py
loggerglue/server.py
loggerglue/version.py
loggerglue.egg-info/PKG-INFO
loggerglue.egg-info/SOURCES.txt
loggerglue.egg-info/dependency_links.txt
loggerglue.egg-info/requires.txt
loggerglue.egg-info/top_level.txt
loggerglue/tests/__init__.py
loggerglue/tests/rfc5424.py