Metadata-Version: 1.0
Name: loggerglue
Version: 0.9
Summary: Syslog protocol (rfc5424 and rfc5425) utilities
Home-page: http://www.evax.fr/
Author: Evax Software
Author-email: contact@evax.fr
License: MIT License
Keywords: syslog,rfc5424,rfc5425,TLS
Platform: UNKNOWN
Classifier: Development Status :: 4 - Beta
Classifier: Intended Audience :: Developers
Classifier: Intended Audience :: System Administrators
Classifier: License :: OSI Approved :: MIT License
Classifier: Programming Language :: Python
Classifier: Operating System :: OS Independent
Classifier: Topic :: System :: Logging
Classifier: Topic :: Internet :: Log Analysis
